pyuvcgen/__init__.py
pyuvcgen/__main__.py
pyuvcgen/generator.py
pyuvcgen/templates/uvc_template/README.md
pyuvcgen/templates/uvc_template/sve.f
pyuvcgen/templates/uvc_template/uvc.f
pyuvcgen/templates/uvc_template/env/top_coverage.sv
pyuvcgen/templates/uvc_template/env/top_env.sv
pyuvcgen/templates/uvc_template/env/top_env_config.sv
pyuvcgen/templates/uvc_template/env/top_env_pkg.sv
pyuvcgen/templates/uvc_template/env/top_scoreboard.sv
pyuvcgen/templates/uvc_template/env/top_vsqr.sv
pyuvcgen/templates/uvc_template/rtl/buffer.sv
pyuvcgen/templates/uvc_template/scripts/makefiles/Makefile.xilinx
pyuvcgen/templates/uvc_template/scripts/setup/setup_xilinx_eda.sh
pyuvcgen/templates/uvc_template/scripts/vivado/probe.tcl
pyuvcgen/templates/uvc_template/scripts/vivado/run.tcl
pyuvcgen/templates/uvc_template/sv/agent.sv
pyuvcgen/templates/uvc_template/sv/config.sv
pyuvcgen/templates/uvc_template/sv/driver.sv
pyuvcgen/templates/uvc_template/sv/if.sv
pyuvcgen/templates/uvc_template/sv/monitor.sv
pyuvcgen/templates/uvc_template/sv/pkg.sv
pyuvcgen/templates/uvc_template/sv/sequence_item.sv
pyuvcgen/templates/uvc_template/sv/sequencer.sv
pyuvcgen/templates/uvc_template/sv/types.sv
pyuvcgen/templates/uvc_template/sv/seqlib/sequence_base.sv
pyuvcgen/templates/uvc_template/tb/tb.sv
pyuvcgen/templates/uvc_template/tests/top_test.sv
pyuvcgen/templates/uvc_template/tests/top_test_pkg.sv
pyuvcgen/templates/uvc_template/tests/top_test_vseq.sv
pyuvcgen/templates/uvc_template_snps/README.md
pyuvcgen/templates/uvc_template_snps/run.tcl
pyuvcgen/templates/uvc_template_snps/sve.f
pyuvcgen/templates/uvc_template_snps/uvc.f
pyuvcgen/templates/uvc_template_snps/env/top_coverage.sv
pyuvcgen/templates/uvc_template_snps/env/top_env.sv
pyuvcgen/templates/uvc_template_snps/env/top_env_config.sv
pyuvcgen/templates/uvc_template_snps/env/top_env_pkg.sv
pyuvcgen/templates/uvc_template_snps/env/top_scoreboard.sv
pyuvcgen/templates/uvc_template_snps/env/top_vsqr.sv
pyuvcgen-1.0.2.dist-info/licenses/LICENSE
pyuvcgen-1.0.2.dist-info/METADATA
pyuvcgen-1.0.2.dist-info/WHEEL
pyuvcgen-1.0.2.dist-info/entry_points.txt
pyuvcgen-1.0.2.dist-info/top_level.txt
pyuvcgen-1.0.2.dist-info/RECORD
