Metadata-Version: 2.4
Name: pyuvcgen
Version: 1.0.2
Summary: Python based UVM-UVC generator
Author: Ciro Bermudez
License: MIT License
Project-URL: Homepage, https://github.com/cirofabianbermudez/pyuvcgen
Requires-Python: >=3.9
License-File: LICENSE
Requires-Dist: Jinja2>=3.1.6
Requires-Dist: PyYAML>=6.0.2
Dynamic: license-file
